nodeclass
