Metadata-Version: 2.1
Name: nodeclass
Version: 0.0.3
Summary: Node classification package
Home-page: https://github.com/migueleci/node_classification
Author: Miguel Romero
Author-email: romeromiguelin@gmail.com
License: MIT
Platform: UNKNOWN
Classifier: Development Status :: 1 - Planning
Classifier: Intended Audience :: Science/Research
Classifier: License :: OSI Approved :: BSD License
Classifier: Operating System :: POSIX :: Linux
Classifier: Programming Language :: Python :: 3
Classifier: Programming Language :: Python :: 3.6
Requires-Python: >=3.6
License-File: LICENSE
